{
    "images": [
        {
            "file_name": "K-001900-010224-016551-031705_0_2_0_2_90_000_200.png",
            "width": 976,
            "height": 1280,
            "imgfile": "K-001900-010224-016551-031705_0_2_0_2_90_000_200.png",
            "drug_N": "K-010224",
            "drug_S": "정상알약",
            "back_color": "연회색 배경",
            "drug_dir": "앞면",
            "light_color": "주백색",
            "camera_la": 90,
            "camera_lo": 0,
            "size": 200,
            "dl_idx": "10200",
            "dl_mapping_code": "K-010224",
            "dl_name": "넥시움정 40mg",
            "dl_name_en": "Nexium Tab. 40mg",
            "img_key": "https://common.health.kr/shared/images/sb_photo/big3/A11AGGGGA527201.jpg",
            "dl_material": "",
            "dl_material_en": "",
            "dl_custom_shape": "",
            "dl_company": "한국아스트라제네카(주)",
            "dl_company_en": "Astrazeneca Korea",
            "di_company_mf": "",
            "di_company_mf_en": "",
            "item_seq": 198700706,
            "di_item_permit_date": "19870323",
            "di_class_no": "",
            "di_etc_otc_code": "",
            "di_edi_code": "",
            "chart": "",
            "drug_shape": "장방형",
            "thick": 2.5,
            "leng_long": 8,
            "leng_short": 4.5,
            "print_front": "BSP",
            "print_back": "5",
            "color_class1": "갈색",
            "color_class2": "",
            "line_front": "",
            "line_back": "",
            "img_regist_ts": "20070910",
            "form_code_name": "나정",
            "mark_code_front_anal": "",
            "mark_code_back_anal": "",
            "mark_code_front_img": "",
            "mark_code_back_img": "",
            "mark_code_front": "",
            "mark_code_back": "",
            "change_date": "20160825",
            "id": 1419
        }
    ],
    "type": "instances",
    "annotations": [
        {
            "area": 29008,
            "iscrowd": 0,
            "bbox": [
                590,
                100,
                230,
                400
            ],
            "category_id": 930010,
            "ignore": 0,
            "segmentation": [],
            "id": 30012,
            "image_id": 1419
        }
    ],
    "categories": [
        {
            "supercategory": "pill",
            "id": 930010,
            "name": "넥시움정 40mg"
        }
    ]
}